captcha_free/__init__.py
captcha_free-0.1.4.dist-info/LICENSE
captcha_free-0.1.4.dist-info/METADATA
captcha_free-0.1.4.dist-info/WHEEL
captcha_free-0.1.4.dist-info/top_level.txt
captcha_free-0.1.4.dist-info/RECORD
