Metadata-Version: 2.1
Name: captcha-free
Version: 0.1.4
Summary: A Selenium WebDriver wrapper that bypasses reCAPTCHA using OpenAI Whisper
Home-page: https://github.com/theriley106/captcha_free
Author: theriley106
Author-email: christopherlambert106@gmail.com
License: MIT
Classifier: Programming Language :: Python :: 3
Classifier: License :: OSI Approved :: MIT License
Classifier: Operating System :: OS Independent
Requires-Python: >=3.6
License-File: LICENSE
Requires-Dist: selenium
Requires-Dist: openai-whisper
Requires-Dist: requests
